aihwkit.libs/libopenblas-r0-f650aae0.3.3.so
aihwkit.libs/libgfortran-91cc3cb1.so.3.0.0
aihwkit.libs/libgomp-a34b3233.so.1.0.0
aihwkit.libs/libquadmath-96973f99.so.0.0.0
aihwkit/VERSION.txt
aihwkit/__init__.py
aihwkit/version.py
aihwkit/exceptions.py
aihwkit/extension/functions.py
aihwkit/extension/__init__.py
aihwkit/experiments/__init__.py
aihwkit/experiments/experiments/inferencing.py
aihwkit/experiments/experiments/__init__.py
aihwkit/experiments/experiments/base.py
aihwkit/experiments/experiments/training.py
aihwkit/experiments/runners/i_local.py
aihwkit/experiments/runners/cloud.py
aihwkit/experiments/runners/metrics.py
aihwkit/experiments/runners/__init__.py
aihwkit/experiments/runners/base.py
aihwkit/experiments/runners/i_metrics.py
aihwkit/experiments/runners/i_cloud.py
aihwkit/experiments/runners/local.py
aihwkit/linalg/__init__.py
aihwkit/linalg/matrix.py
aihwkit/utils/fitting.py
aihwkit/utils/visualization_web.py
aihwkit/utils/__init__.py
aihwkit/utils/analog_info.py
aihwkit/utils/visualization.py
aihwkit/utils/export.py
aihwkit/utils/legacy.py
aihwkit/simulator/noise_models.py
aihwkit/simulator/__init__.py
aihwkit/simulator/rpu_base.cpython-310-x86_64-linux-gnu.so
aihwkit/simulator/digital_low_precision/config_utils.py
aihwkit/simulator/digital_low_precision/quantizers.py
aihwkit/simulator/digital_low_precision/range_estimators.py
aihwkit/simulator/digital_low_precision/quantization_manager.py
aihwkit/simulator/digital_low_precision/__init__.py
aihwkit/simulator/digital_low_precision/base_quantized_model.py
aihwkit/simulator/digital_low_precision/utils.py
aihwkit/simulator/digital_low_precision/base_quantized_classes.py
aihwkit/simulator/digital_low_precision/hijacker.py
aihwkit/simulator/configs/helpers.py
aihwkit/simulator/configs/configs.py
aihwkit/simulator/configs/compounds.py
aihwkit/simulator/configs/__init__.py
aihwkit/simulator/configs/utils.py
aihwkit/simulator/configs/devices.py
aihwkit-1.0.0.dist-info/WHEEL
aihwkit-1.0.0.dist-info/top_level.txt
aihwkit-1.0.0.dist-info/RECORD
aihwkit-1.0.0.dist-info/METADATA
aihwkit-1.0.0.dist-info/licenses/LICENSE.txt
