Metadata-Version: 2.4
Name: aihwkit
Version: 1.0.0
Summary: IBM Analog Hardware Acceleration Kit
Home-page: https://github.com/IBM/aihwkit
Author: IBM Research
Author-email: aihwkit@us.ibm.com
License: MIT
Keywords: ai,analog,rpu,torch,memristor,pcm,reram,crossbar,in-memory,nvm,non-von-neumann,non-volatile memory,phase-change material
Classifier: Development Status :: 4 - Beta
Classifier: Environment :: Console
Classifier: Environment :: GPU :: NVIDIA CUDA
Classifier: Intended Audience :: Science/Research
Classifier: License :: OSI Approved :: MIT License
Classifier: Operating System :: MacOS
Classifier: Operating System :: Microsoft :: Windows
Classifier: Operating System :: POSIX :: Linux
Classifier: Programming Language :: Python :: 3 :: Only
Classifier: Topic :: Scientific/Engineering
Classifier: Topic :: Scientific/Engineering :: Artificial Intelligence
Classifier: Typing :: Typed
Requires-Python: >=3.7
License-File: LICENSE.txt
Requires-Dist: torch>=1.9
Requires-Dist: torchvision
Requires-Dist: scipy
Requires-Dist: requests<3,>=2.25
Requires-Dist: numpy>=1.22
Requires-Dist: protobuf>=4.21.6
Provides-Extra: visualization
Requires-Dist: matplotlib>=3.0; extra == "visualization"
Provides-Extra: fitting
Requires-Dist: lmfit; extra == "fitting"
Provides-Extra: bert
Requires-Dist: transformers; extra == "bert"
Requires-Dist: evaluate; extra == "bert"
Requires-Dist: datasets; extra == "bert"
Requires-Dist: wandb; extra == "bert"
Requires-Dist: tensorboard; extra == "bert"
Dynamic: author
Dynamic: author-email
Dynamic: classifier
Dynamic: description
Dynamic: description-content-type
Dynamic: home-page
Dynamic: keywords
Dynamic: license
Dynamic: license-file
Dynamic: provides-extra
Dynamic: requires-dist
Dynamic: requires-python
Dynamic: summary
